clandestino_elasticsearch/__init__.py
clandestino_elasticsearch/infra.py
clandestino_elasticsearch/ref.py
clandestino_elasticsearch/repository.py
clandestino_elasticsearch-0.1.1.dist-info/LICENSE
clandestino_elasticsearch-0.1.1.dist-info/METADATA
clandestino_elasticsearch-0.1.1.dist-info/WHEEL
clandestino_elasticsearch-0.1.1.dist-info/RECORD
