Metadata-Version: 2.1
Name: clandestino-elasticsearch
Version: 0.1.1
Summary: Clandestino Elasticsearch implementation
Author: XimitGaia
Author-email: im.ximit@gmail.com
Requires-Python: >=3.11,<4.0
Classifier: Programming Language :: Python :: 3
Classifier: Programming Language :: Python :: 3.11
Requires-Dist: aiohttp (>=3.9.3,<4.0.0)
Requires-Dist: clandestino-interfaces (>=0.1.0,<0.2.0)
Requires-Dist: elasticsearch (>=8.12.1,<9.0.0)
Requires-Dist: python-decouple (>=3.8,<4.0)
